llamp/__init__.py
llamp/llms/__init__.py
llamp/llms/base_llm_system.py
llamp/llms/base_system.py
llamp/llms/human.py
llamp/llms/api/__init__.py
llamp/llms/api/anthropic_chat.py
llamp/llms/api/anthropic_text.py
llamp/llms/api/cerebras_chat_text.py
llamp/llms/api/cohere_chat.py
llamp/llms/api/cohere_chat_text.py
llamp/llms/api/cohere_text.py
llamp/llms/api/nvidia_chat_text.py
llamp/llms/api/openai_chat.py
llamp/llms/api/openai_chat_text.py
llamp/llms/api/openai_chat_text_sampling.py
llamp/llms/api/openai_text.py
llamp/llms/local/__init__.py
llamp/llms/local/minichat.py
llamp/llms/local/mistral_multi_gpu.py
llamp/llms/local/open_mistral_orca.py
llamp/llms/local/orca2.py
llamp/llms/local/qwen.py
llamp/llms/local/qwen_multi_gpu.py
llamp/llms/local/test_minichat_agent.py
llamp/llms/local/vllm_chat.py
llamp/llms/local/yi.py
llamp-0.0.6.dist-info/METADATA
llamp-0.0.6.dist-info/WHEEL
llamp-0.0.6.dist-info/top_level.txt
llamp-0.0.6.dist-info/RECORD
