Metadata-Version: 2.2
Name: llamp
Version: 0.0.6
Summary: LLAMP - Large Language Model for Planning and Acting
Author-email: Nikolai Rozanov <nikolai.rozanov@gmail.com>
Requires-Dist: transformers>=4.48.2
Requires-Dist: vllm>=0.7.1
Requires-Dist: tiktoken>=0.7.0
